threebrainpy/__init__.py
threebrainpy/_version.py
threebrainpy/junk.py
threebrainpy/core/__init__.py
threebrainpy/core/brain.py
threebrainpy/core/colormap.py
threebrainpy/core/constants.py
threebrainpy/core/geom_datacube.py
threebrainpy/core/geom_placeholder.py
threebrainpy/core/geom_sphere.py
threebrainpy/core/geom_surface.py
threebrainpy/core/geom_template.py
threebrainpy/core/group.py
threebrainpy/core/keyframe.py
threebrainpy/core/mat44.py
threebrainpy/core/vec3.py
threebrainpy/templates/__init__.py
threebrainpy/templates/favicon.ico
threebrainpy/templates/index.html
threebrainpy/templates/launch.zip
threebrainpy/templates/linux.sh
threebrainpy/templates/mac.command
threebrainpy/templates/redirect.html
threebrainpy/templates/simple_server.py
threebrainpy/templates/windows.bat
threebrainpy/templates/lib/htmlwidgets-1.6.2/htmlwidgets.js
threebrainpy/templates/lib/three-brain-1.0.0/120.threebrain.js
threebrainpy/templates/lib/three-brain-1.0.0/120.threebrain.js.LICENSE.txt
threebrainpy/templates/lib/three-brain-1.0.0/120.threebrain.js.map
threebrainpy/templates/lib/three-brain-1.0.0/392.threebrain.js
threebrainpy/templates/lib/three-brain-1.0.0/392.threebrain.js.map
threebrainpy/templates/lib/three-brain-1.0.0/856.threebrain.js
threebrainpy/templates/lib/three-brain-1.0.0/856.threebrain.js.LICENSE.txt
threebrainpy/templates/lib/three-brain-1.0.0/856.threebrain.js.map
threebrainpy/templates/lib/three-brain-1.0.0/manifest.json
threebrainpy/templates/lib/three-brain-1.0.0/threebrain.js
threebrainpy/templates/lib/three-brain-1.0.0/threebrain.js.LICENSE.txt
threebrainpy/templates/lib/three-brain-1.0.0/threebrain.js.map
threebrainpy/templates/lib/threebrain_data-0/__global_data/ContinuousSample.json
threebrainpy/templates/lib/threebrain_data-0/__global_data/FSColorLUT.json
threebrainpy/templates/lib/threebrain_data-0/__global_data/FreeSurferColorLUT.json
threebrainpy/templates/lib/threejs_brain-binding-1.0.1.9004/threejs_brain.js
threebrainpy/utils/__init__.py
threebrainpy-0.1.0.dist-info/LICENSE.txt
threebrainpy-0.1.0.dist-info/METADATA
threebrainpy-0.1.0.dist-info/WHEEL
threebrainpy-0.1.0.dist-info/top_level.txt
threebrainpy-0.1.0.dist-info/RECORD
