Metadata-Version: 2.1
Name: threebrainpy
Version: 0.1.0
Summary: Your Advanced Electrode Localizer Viewer for Python
Home-page: https://github.com/dipterix/threeBrainPy
Author: Zhengjia Wang
Author-email: dipterix.wang@gmail.com
License: Mozilla Public License 2.0 (MPL 2.0)
Project-URL: Project Website, https://yael.wiki/
Project-URL: Source, https://github.com/dipterix/threeBrainPy/
Project-URL: Bug Reports, https://github.com/dipterix/threeBrainPy/issues
Keywords: iEEG,DBS,Visualization,Neuroscience,Electrophysiology,Electrode,Localizer
Classifier: Development Status :: 3 - Alpha
Classifier: Intended Audience :: Developers
Classifier: Intended Audience :: Science/Research
Classifier: Topic :: Multimedia :: Graphics :: 3D Rendering
Classifier: Topic :: Scientific/Engineering :: Human Machine Interfaces
Classifier: Topic :: Scientific/Engineering :: Visualization
Classifier: Operating System :: OS Independent
Classifier: License :: OSI Approved :: Mozilla Public License 2.0 (MPL 2.0)
Classifier: Programming Language :: Python :: 3
Requires-Python: >=3
License-File: LICENSE.txt
Requires-Dist: numpy
Requires-Dist: nibabel
Requires-Dist: pandas
Requires-Dist: matplotlib
